{
  "askcliStatesVersion": "2020-03-31",
  "profiles": {
    "default": {
      "skillInfrastructure": {
        "@ask-cli/lambda-deployer": {
          "deployState": {
            "default": {
              "iamRole": "arn:aws:iam::679180307287:role/service-role/ChatsinoAlexa-role-rtdbd1zy",
              "lambda": {
                "arn": "arn:aws:lambda:us-east-1:679180307287:function:ChatsinoAlexa",
                "lastModified": "2020-10-15T16:33:24.906+0000",
                "revisionId": "23b5c3ab-018f-422a-a959-d9c93b0c8ab5"
              }
            }
          }
        }
      },
      "skillId": "amzn1.ask.skill.a575fab8-3483-4b15-adba-7814aaf54b70",
      "skillMetadata": {
        "lastDeployHash": "DUfcvzRSzXD0rK+KgGdiJoL0e0s="
      },
      "code": {
        "default": {
          "lastDeployHash": "tTtvsCI1765dyCOsyakAxwaysQU="
        }
      }
    }
  }
}